{
  "ThursdaySeries": "culto série RESTITUIÇÃO",
  "last_updated": "2026-05-08T03:54:14.987505",
  "latest_videos": [],
  "latest_completed_live_streams": [
    {
      "title": "RESTITUIÇÃO | LÚCIO CAMILLO | PRESENÇA IGREJA CRISTÃ",
      "thumbnail": "https://i.ytimg.com/vi/bt_lTsIhHQA/hqdefault_live.jpg",
      "url": "https://www.youtube.com/watch?v=bt_lTsIhHQA"
    },
    {
      "title": "A TUA MESA CURA | LÚCIO CAMILLO | PRESENÇA IGREJA CRISTÃ",
      "thumbnail": "https://i.ytimg.com/vi/P0Xu32WXJGM/hqdefault.jpg",
      "url": "https://www.youtube.com/watch?v=P0Xu32WXJGM"
    },
    {
      "title": "VENCENDO AS PROVAÇÕES | MICHEL NASCIMENTO | PRESENÇA IGREJA CRISTÃ",
      "thumbnail": "https://i.ytimg.com/vi/FX4lYdbG_Ns/hqdefault.jpg",
      "url": "https://www.youtube.com/watch?v=FX4lYdbG_Ns"
    }
  ],
  "current_live_stream": null
}